{
  "clpercentage": "",
  "clause": [
    {
      "id": "cls.1",
      "name": "Global",
      "type": "rule",
      "allowed": "YES",
      "execution": "PRE,CLA",
      "coverage": {
        "id": "cvg.1.1",
        "coverageid": "123",
        "name": "Any coverage",
        "allowed": "3",
        "module": "P",
        "clpercentage": "",
        "selected": "YES",
        "autoselect": "",
        "condition": [
          {
            "id": "cnd.1.1.1",
            "field": "member.inceptiondate",
            "op": "LE",
            "opType": "date",
            "value": "",
            "module": "P",
            "dynValue": "check_global_rule('INC')",
            "clfactor": "10",
            "mandatory": "",
            "method": "MEMBER.INCEPTION_DATE",
            "source": "TABLE",
            "fieldData": "",
            "unit": "",
            "result": "",
            "display": {
              "id": "dsp.1.1.1.1",
              "target": "",
              "prelabel": "Member inception date",
              "control": "",
              "type": "",
              "default": "",
              "postlabel": "admission date",
              "jscall": ""
            }
          },
          {
            "id": "cnd.1.1.2",
            "field": "policy.startdate",
            "op": "LE",
            "opType": "date",
            "value": "",
            "module": "P",
            "dynValue": "check_global_rule('STD')",
            "clfactor": "10",
            "mandatory": "",
            "method": "MEMBER.EFFECTIVE_FROM_DATE",
            "source": "TABLE",
            "fieldData": "",
            "unit": "",
            "result": "",
            "display": {
              "id": "dsp.1.1.2.1",
              "target": "",
              "prelabel": "Policy start date",
              "control": "",
              "type": "",
              "default": "",
              "postlabel": "admission date",
              "jscall": ""
            }
          },
          {
            "id": "cnd.1.1.3",
            "field": "policy.enddate",
            "op": "GE",
            "opType": "date",
            "value": "",
            "module": "P",
            "dynValue": "check_global_rule('END')",
            "clfactor": "10",
            "mandatory": "",
            "method": "MEMBER.EFFECTIVE_TO_DATE",
            "source": "TABLE",
            "fieldData": "",
            "unit": "",
            "result": "",
            "display": {
              "id": "dsp.1.1.3.1",
              "target": "",
              "prelabel": "Policy end date",
              "control": "",
              "type": "",
              "default": "",
              "postlabel": "admission date",
              "jscall": ""
            }
          },
          {
            "id": "cnd.1.1.4",
            "field": "member.status",
            "op": "EQ",
            "opType": "text",
            "value": "POA",
            "module": "P",
            "dynValue": "check_global_rule('~')",
            "clfactor": "10",
            "mandatory": "",
            "method": "MEMBER.MEM_STATUS",
            "source": "TABLE",
            "fieldData": "",
            "unit": "",
            "result": "",
            "configure": "NO",
            "display": {
              "id": "dsp.1.1.4.1",
              "target": "dynValue,1",
              "prelabel": "Member status",
              "control": "select",
              "type": "",
              "default": "POA",
              "optText": "Active",
              "altText": "Active",
              "optVal": "POA",
              "postlabel": "",
              "jscall": "",
              "lookup": "policyStatus"
            }
          },
          {
            "id": "cnd.1.1.5",
            "field": "request.amount",
            "op": "LE",
            "opType": "numeric",
            "value": "",
            "module": "P",
            "dynValue": "check_global_rule('REQ')",
            "clfactor": "10",
            "mandatory": "",
            "method": "get_approved_amount()",
            "source": "PACKAGE",
            "fieldData": "",
            "unit": "",
            "result": "",
            "display": {
              "id": "dsp.1.1.5.1",
              "target": "",
              "prelabel": "Approved amount",
              "control": "",
              "type": "",
              "default": "",
              "postlabel": "available Sum Insured",
              "jscall": ""
            }
          },
          {
            "id": "cnd.1.1.6",
            "field": "aproved.amount",
            "op": "GE",
            "opType": "numeric",
            "value": "",
            "module": "P",
            "dynValue": "check_global_rule('APR')",
            "clfactor": "10",
            "mandatory": "",
            "method": "REQUEST.REQUESTED_AMOUNT",
            "source": "TABLE",
            "fieldData": "",
            "unit": "",
            "result": "",
            "display": {
              "id": "dsp.1.1.6.1",
              "target": "",
              "prelabel": "Requested amount",
              "control": "",
              "type": "",
              "default": "",
              "postlabel": "Approved amount",
              "jscall": ""
            }
          },
          {
            "id": "cnd.1.1.17",
            "field": "received.date",
            "op": "",
            "opType": "",
            "value": "",
            "module": "P",
            "dynValue": "check_pat_validation_days('~','~','BCK')",
            "clfactor": "10",
            "mandatory": "",
            "method": "",
            "source": "",
            "fieldData": "",
            "unit": "",
            "result": "",
            "display": [
              {
                "id": "dsp.1.1.17.1",
                "target": "dynValue,1",
                "prelabel": "New Pre-auth admission period for back date Preapprovals(Pre-auth received date - Activity start date) within Country",
                "control": "input",
                "type": "text",
                "default": "",
                "postlabel": "days, outside Country",
                "jscall": "onkeyup=isNumeric(this)",
                "lookup": ""
              },
              {
                "id": "dsp.1.1.17.2",
                "target": "dynValue,2",
                "prelabel": "",
                "control": "input",
                "type": "text",
                "default": "",
                "postlabel": "days",
                "jscall": "onkeyup=isNumeric(this)",
                "lookup": ""
              }
            ]
          },
          {
            "id": "cnd.1.1.12",
            "field": "received.date",
            "op": "",
            "opType": "",
            "value": "",
            "module": "P",
            "dynValue": "check_clm_validation_days('~','~','~','~','~','~','~')",
            "clfactor": "10",
            "mandatory": "",
            "method": "",
            "source": "",
            "fieldData": "",
            "unit": "",
            "result": "",
            "display": [
              {
                "id": "dsp.1.1.12.1",
                "target": "dynValue,1",
                "prelabel": "Claim submission period",
                "control": "select",
                "type": "",
                "default": "",
                "optText": "Network Claim",
                "altText": "Network Claim",
                "optVal": "CNH",
                "postlabel": "",
                "jscall": "",
                "lookup": ""
              },
              {
                "id": "dsp.1.1.12.2",
                "target": "dynValue,2",
                "prelabel": "before",
                "control": "input",
                "type": "text",
                "default": "",
                "postlabel": "",
                "jscall": "onkeyup=isNumeric(this)",
                "lookup": ""
              },
              {
                "id": "dsp.1.1.12.3",
                "target": "dynValue,3",
                "prelabel": "",
                "control": "select",
                "type": "",
                "default": "",
                "optText": "Select From The list,Day Of The Next Month,Calendar Days,Next Month Calendar days",
                "altText": "Select From The list,Day Of The Next Month,Calendar Days,Next Month Calendar days",
                "optVal": ",MON,DAYS,NCD",
                "postlabel": "within Country,",
                "jscall": "",
                "lookup": ""
              },
              {
                "id": "dsp.1.1.!2.4",
                "target": "dynValue,4",
                "prelabel": "",
                "control": "input",
                "type": "text",
                "default": "",
                "postlabel": "days outside Country",
                "jscall": "onkeyup=isNumeric(this)",
                "lookup": ""
              },
              {
                "id": "dsp.1.1.12.5",
                "target": "dynValue,5",
                "prelabel": "<br> and",
                "control": "select",
                "type": "",
                "default": "",
                "optText": "Member Claim",
                "altText": "Member Claim",
                "optVal": "CTM",
                "postlabel": "",
                "jscall": "",
                "lookup": ""
              },
              {
                "id": "dsp.1.1.12.6",
                "target": "dynValue,6",
                "prelabel": "",
                "control": "input",
                "type": "text",
                "default": "",
                "postlabel": "days within Country,",
                "jscall": "onkeyup=isNumeric(this)",
                "lookup": ""
              },
              {
                "id": "dsp.1.1.12.7",
                "target": "dynValue,7",
                "prelabel": "",
                "control": "input",
                "type": "text",
                "default": "",
                "postlabel": "days outside Country",
                "jscall": "onkeyup=isNumeric(this)",
                "lookup": ""
              }
            ]
          },
          {
            "id": "cnd.1.1.13",
            "field": "claim.resubmission",
            "op": "",
            "opType": "",
            "value": "",
            "module": "P",
            "dynValue": "CLAIM_RESUB_DAYS_VALID('~','~')",
            "clfactor": "10",
            "mandatory": "",
            "method": "",
            "source": "",
            "fieldData": "",
            "unit": "",
            "result": "",
            "display": [
              {
                "id": "dsp.1.1.13.1",
                "target": "dynValue,1",
                "prelabel": "Claim resubmission period",
                "control": "select",
                "type": "",
                "default": "",
                "optText": "Network Claim",
                "altText": "Network Claim",
                "optVal": "CNH",
                "postlabel": "",
                "jscall": "",
                "lookup": ""
              },
              {
                "id": "dsp.1.1.13.2",
                "target": "dynValue,2",
                "prelabel": "",
                "control": "input",
                "type": "text",
                "default": "",
                "postlabel": "calender days from the date of payment within Country .",
                "jscall": "onkeyup=isNumeric(this)",
                "lookup": ""
              }
            ]
          },
          {
            "id": "cnd.1.1.14",
            "field": "assistance.cover1",
            "op": "",
            "opType": "",
            "value": "",
            "module": "P",
            "dynValue": "check_pat_validation_days('~','~','FUT')",
            "clfactor": "10",
            "mandatory": "",
            "method": "",
            "source": "",
            "fieldData": "",
            "unit": "",
            "result": "",
            "display": [
              {
                "id": "dsp.1.1.14.1",
                "target": "dynValue,1",
                "prelabel": "Pre-auth admission period for future date Preapprovals(Activity start date - Pre-auth received date) within Country",
                "control": "input",
                "type": "text",
                "default": "",
                "postlabel": "days, outside Country",
                "jscall": "onkeyup=isNumeric(this)",
                "lookup": ""
              },
              {
                "id": "dsp.1.1.14.2",
                "target": "dynValue,2",
                "prelabel": "",
                "control": "input",
                "type": "text",
                "default": "",
                "postlabel": "days",
                "jscall": "onkeyup=isNumeric(this)",
                "lookup": ""
              }
            ]
          },
          {
            "id": "cnd.1.1.15",
            "field": "assistance.cover1",
            "op": "",
            "opType": "",
            "value": "",
            "module": "P",
            "dynValue": "check_pat_validation_days('~','~','ENP')",
            "clfactor": "10",
            "mandatory": "",
            "method": "",
            "source": "",
            "fieldData": "",
            "unit": "",
            "result": "",
            "display": [
              {
                "id": "dsp.1.1.15.1",
                "target": "dynValue,1",
                "prelabel": "Enhancement submission period in",
                "control": "input",
                "type": "text",
                "default": "",
                "postlabel": "days within Country",
                "jscall": "onkeyup=isNumeric(this)",
                "lookup": ""
              },
              {
                "id": "dsp.1.1.15.2",
                "target": "dynValue,2",
                "prelabel": "",
                "control": "input",
                "type": "text",
                "default": "",
                "postlabel": "days outside Country from initial Pre-approval received date to Enhancement Received date",
                "jscall": "onkeyup=isNumeric(this)",
                "lookup": ""
              }
            ]
          },
          {
            "id": "cnd.1.1.16",
            "field": "assistance.cover1",
            "op": "",
            "opType": "",
            "value": "",
            "module": "P",
            "dynValue": "check_pat_validation_days('~','~','ENH')",
            "clfactor": "10",
            "mandatory": "",
            "method": "",
            "source": "",
            "fieldData": "",
            "unit": "",
            "result": "",
            "display": {
              "id": "dsp.1.1.16.1",
              "target": "dynValue,1",
              "prelabel": "No. of Enhancements allowed",
              "control": "input",
              "type": "text",
              "default": "",
              "postlabel": "for a Pre-Approval",
              "jscall": "onkeyup=isNumeric(this)",
              "lookup": ""
            }
          }
        ],
        "action": {
          "id": "act.1.1.1",
          "name": "ruleengineaction"
        }
      }
    },
    {
      "id": "cls.10",
      "name": "In-Patient",
      "allowed": "NO",
      "type": "rule",
      "execution": "PRE,CLA",
      "coverage": [
        {
          "id": "cvg.10.15",
          "name": "In-Patient",
          "allowed": "~",
          "module": "P",
          "clpercentage": "",
          "selected": "YES",
          "autoselect": "A|34",
          "display": {
            "id": "dsp.10.15.1",
            "target": "allowed,1",
            "prelabel": "",
            "control": "radiogroup",
            "type": "single",
            "default": "2",
            "optText": "Pay,Don't Pay,Pay Conditionally",
            "altText": "Pay,Don't Pay,Pay Conditionally",
            "optVal": "1,2,3",
            "postlabel": "",
            "jscall": "onclick=showHideCondition(this)"
          },
          "condition": [
            {
              "id": "cnd.10.15.1",
              "field": "oc1",
              "op": "",
              "opType": "",
              "value": "",
              "dynValue": "check_authorization('NOTGIVEN','~')",
              "clfactor": "10",
              "mandatory": "NO",
              "method": "get_request_state()",
              "source": "PACKAGE",
              "module": "P",
              "fieldData": "",
              "unit": "",
              "result": "",
              "configure": "NO",
              "display": {
                "id": "dsp.10.15.1.1",
                "target": "dynValue,2",
                "prelabel": "Authorization  required",
                "control": "select",
                "type": "text",
                "disabled": "",
                "default": "N",
                "optText": "Yes,No",
                "altText": "Yes,No",
                "optVal": "Y,N",
                "postlabel": "",
                "jscall": "",
                "lookup": ""
              }
            },
            {
              "id": "cnd.10.15.2",
              "field": "assistance.cover1",
              "value": "",
              "dynValue": "validate_ip_limit('IPT','~','~','~','~','~','~','~','~','~','~','~','~','~','~','~','~','~','~')",
              "clfactor": "10",
              "mandatory": "NO",
              "method": "get_request_country()",
              "source": "PACKAGE",
              "module": "P",
              "fieldData": "",
              "unit": "",
              "result": "",
              "configure": "NO",
              "display": [
                {
                  "id": "dsp.10.15.2.1",
                  "target": "dynValue,2",
                  "prelabel": "Limit amount",
                  "control": "select",
                  "type": "single",
                  "default": "LE",
                  "optText": "<=",
                  "altText": "LE",
                  "optVal": "LE",
                  "postlabel": "",
                  "jscall": "",
                  "lookup": ""
                },
                {
                  "id": "dsp.10.15.2.2",
                  "target": "dynValue,3",
                  "prelabel": "",
                  "control": "select",
                  "type": "single",
                  "default": "",
                  "optText": "fixed amount,% of Sum Insured",
                  "altText": "fixed amount,% of Sum Insured",
                  "optVal": "FA,SI",
                  "postlabel": "",
                  "jscall": ""
                },
                {
                  "id": "dsp.10.15.2.3",
                  "target": "dynValue,4",
                  "prelabel": "",
                  "control": "input",
                  "type": "text",
                  "default": "",
                  "postlabel": "",
                  "jscall": "onkeyup=isNumeric(this)",
                  "lookup": ""
                },
                {
                  "id": "dsp.10.15.2.4",
                  "target": "dynValue,5",
                  "prelabel": "",
                  "control": "input",
                  "type": "text",
                  "default": "OMR",
                  "optText": "",
                  "altText": "",
                  "optVal": "",
                  "disabled": "true",
                  "postlabel": "",
                  "jscall": ""
                },
                {
                  "id": "dsp.10.15.2.5",
                  "target": "",
                  "prelabel": "",
                  "control": "image",
                  "type": "image",
                  "imagepath": "EditIcon.gif",
                  "alt": "Select Currency",
                  "default": "",
                  "postlabel": "",
                  "jscall": "onclick=openRadioList('dsp.18.3.3.3','CURRENCY_GROUP','option')"
                },
                {
                  "id": "dsp.10.15.2.6",
                  "target": "dynValue,6",
                  "prelabel": "per claim Limit amount",
                  "control": "select",
                  "type": "single",
                  "default": "LE",
                  "optText": "<=",
                  "altText": "LE",
                  "optVal": "LE",
                  "postlabel": " ",
                  "jscall": "",
                  "lookup": ""
                },
                {
                  "id": "dsp.10.15.2.7",
                  "target": "dynValue,7",
                  "prelabel": "",
                  "control": "select",
                  "type": "single",
                  "default": "",
                  "optText": "fixed amount,% of Sum Insured",
                  "altText": "fixed amount,% of Sum Insured",
                  "optVal": "FA,SI",
                  "postlabel": "",
                  "jscall": ""
                },
                {
                  "id": "dsp.10.15.2.8",
                  "target": "dynValue,8",
                  "prelabel": "",
                  "control": "input",
                  "type": "text",
                  "default": "",
                  "postlabel": "",
                  "jscall": "onkeyup=isNumeric(this)",
                  "lookup": ""
                },
                {
                  "id": "dsp.10.15.2.9",
                  "target": "dynValue,9",
                  "prelabel": "",
                  "control": "input",
                  "type": "text",
                  "default": "OMR",
                  "optText": "",
                  "altText": "",
                  "optVal": "",
                  "disabled": "true",
                  "postlabel": "",
                  "jscall": ""
                },
                {
                  "id": "dsp.10.15.2.10",
                  "target": "",
                  "prelabel": "",
                  "control": "image",
                  "type": "image",
                  "imagepath": "EditIcon.gif",
                  "alt": "Select Currency",
                  "default": "",
                  "postlabel": "",
                  "jscall": "onclick=openRadioList('dsp.10.15.2.9','CURRENCY_GROUP','option')"
                },
                {
                  "id": "dsp.10.15.2.11",
                  "target": "dynValue,10",
                  "prelabel": "per policy and <br> Co-pay ",
                  "control": "select",
                  "type": "single",
                  "default": "EQ",
                  "optText": "=",
                  "altText": "EQ",
                  "optVal": "EQ",
                  "postlabel": "",
                  "jscall": "",
                  "lookup": ""
                },
                {
                  "id": "dsp.10.15.2.12",
                  "target": "dynValue,11",
                  "prelabel": "",
                  "control": "input",
                  "type": "text",
                  "default": "",
                  "postlabel": "%",
                  "jscall": "onkeyup=isNumeric(this)",
                  "lookup": ""
                },
                {
                  "id": "dsp.10.15.2.13",
                  "target": "dynValue,12",
                  "prelabel": "with deductable amount",
                  "control": "select",
                  "type": "single",
                  "default": "EQ",
                  "optText": "=",
                  "altText": "EQ",
                  "optVal": "EQ",
                  "postlabel": "",
                  "jscall": "",
                  "lookup": ""
                },
                {
                  "id": "dsp.10.15.2.14",
                  "target": "dynValue,13",
                  "prelabel": "",
                  "control": "input",
                  "type": "text",
                  "default": "",
                  "postlabel": "",
                  "jscall": "onkeyup=isNumeric(this)",
                  "lookup": ""
                },
                {
                  "id": "dsp.10.15.2.15",
                  "target": "dynValue,14",
                  "prelabel": "",
                  "control": "input",
                  "type": "text",
                  "default": "OMR",
                  "optText": "",
                  "altText": "",
                  "optVal": "OMR",
                  "disabled": "true",
                  "postlabel": "",
                  "jscall": ""
                },
                {
                  "id": "dsp.10.15.2.16",
                  "target": "",
                  "prelabel": "",
                  "control": "image",
                  "type": "image",
                  "imagepath": "EditIcon.gif",
                  "alt": "Select Currency",
                  "default": "",
                  "postlabel": "",
                  "jscall": "onclick=openRadioList('dsp.10.15.2.15','CURRENCY_GROUP','option')"
                },
                {
                  "id": "dsp.10.15.2.17",
                  "target": "dynValue,15",
                  "prelabel": "<br>",
                  "control": "select",
                  "type": "single",
                  "default": "",
                  "optText": "MIN,MAX,BOTH",
                  "altText": "MIN,MAX,BOTH",
                  "optVal": "MIN,MAX,BOTH",
                  "postlabel": " ",
                  "jscall": ""
                },
                {
                  "id": "dsp.10.15.2.19",
                  "target": "dynValue,16",
                  "prelabel": "with max copayment",
                  "control": "input",
                  "type": "text",
                  "default": "",
                  "postlabel": "",
                  "jscall": "onkeyup=isNumeric(this)",
                  "lookup": ""
                },
                {
                  "id": "dsp.10.15.2.20",
                  "target": "dynValue,17",
                  "prelabel": "",
                  "control": "input",
                  "type": "text",
                  "default": "OMR",
                  "optText": "",
                  "altText": "",
                  "optVal": "OMR",
                  "disabled": "true",
                  "postlabel": "",
                  "jscall": ""
                },
                {
                  "id": "dsp.10.15.2.21",
                  "target": "",
                  "prelabel": "",
                  "control": "image",
                  "type": "image",
                  "imagepath": "EditIcon.gif",
                  "alt": "Select Currency",
                  "default": "",
                  "postlabel": "",
                  "jscall": "onclick=openRadioList('dsp.10.15.2.20','CURRENCY_GROUP','option')"
                },
                {
                  "id": "dsp.10.15.2.23",
                  "target": "dynValue,18",
                  "prelabel": "per claim and with max copayment",
                  "control": "input",
                  "type": "text",
                  "default": "",
                  "postlabel": "",
                  "jscall": "onkeyup=isNumeric(this)",
                  "lookup": ""
                },
                {
                  "id": "dsp.10.15.2.24",
                  "target": "dynValue,19",
                  "prelabel": "",
                  "control": "input",
                  "type": "text",
                  "default": "OMR",
                  "optText": "",
                  "altText": "",
                  "optVal": "OMR",
                  "disabled": "true",
                  "postlabel": "",
                  "jscall": ""
                },
                {
                  "id": "dsp.10.15.2.25",
                  "target": "",
                  "prelabel": "",
                  "control": "image",
                  "type": "image",
                  "imagepath": "EditIcon.gif",
                  "alt": "Select Currency",
                  "default": "",
                  "postlabel": "per policy",
                  "jscall": "onclick=openRadioList('dsp.10.15.2.24','CURRENCY_GROUP','option')"
                }
              ]
            }
          ]
        },
        {
          "id": "cvg.10.5",
          "name": "Surgery, Anaesthesiology & Surgeon's Fees",
          "allowed": "~",
          "module": "P",
          "clpercentage": "",
          "selected": "YES",
          "autoselect": "A|35|A|3|A|36",
          "display": {
            "id": "dsp.10.5.1",
            "target": "allowed,1",
            "prelabel": "",
            "control": "radiogroup",
            "type": "single",
            "default": "2",
            "optText": "Pay,Don't Pay,Pay Conditionally",
            "altText": "Pay,Don't Pay,Pay Conditionally",
            "optVal": "1,2,3",
            "postlabel": "",
            "jscall": "onclick=showHideCondition(this)"
          },
          "condition": [
            {
              "id": "cnd.10.5.1",
              "field": "gc2",
              "op": "",
              "opType": "",
              "value": "",
              "dynValue": "check_ip_op_limit('A|11000','~','~','~','~','~','~','~','~','~','~','~')",
              "clfactor": "10",
              "mandatory": "",
              "method": "get_request_state()",
              "source": "PACKAGE",
              "module": "P",
              "fieldData": "",
              "unit": "",
              "result": "",
              "configure": "NO",
              "display": [
                {
                  "id": "dsp.10.5.1.1",
                  "target": "dynValue,2",
                  "prelabel": "Surgery charges Limit amount",
                  "control": "select",
                  "type": "single",
                  "default": "LE",
                  "optText": "<=",
                  "altText": "LE",
                  "optVal": "LE",
                  "postlabel": "",
                  "jscall": "",
                  "lookup": ""
                },
                {
                  "id": "dsp.10.5.1.2",
                  "target": "dynValue,3",
                  "prelabel": "",
                  "control": "select",
                  "type": "single",
                  "default": "",
                  "optText": "fixed amount,% of Sum Insured",
                  "altText": "fixed amount,% of Sum Insured",
                  "optVal": "FA,SI",
                  "postlabel": "",
                  "jscall": ""
                },
                {
                  "id": "dsp.10.5.1.3",
                  "target": "dynValue,4",
                  "prelabel": "",
                  "control": "input",
                  "type": "text",
                  "default": "",
                  "postlabel": "",
                  "jscall": "onkeyup=isNumeric(this)",
                  "lookup": ""
                },
                {
                  "id": "dsp.10.5.1.4",
                  "target": "dynValue,5",
                  "prelabel": "",
                  "control": "input",
                  "type": "text",
                  "default": "OMR",
                  "optText": "",
                  "altText": "",
                  "optVal": "",
                  "disabled": "true",
                  "postlabel": "",
                  "jscall": ""
                },
                {
                  "id": "dsp.10.5.1.5",
                  "target": "",
                  "prelabel": "",
                  "control": "image",
                  "type": "image",
                  "imagepath": "EditIcon.gif",
                  "alt": "Select Currency",
                  "default": "",
                  "postlabel": "and",
                  "jscall": "onclick=openRadioList('dsp.10.5.1.4','CURRENCY_GROUP','option')"
                },
                {
                  "id": "dsp.10.5.1.6",
                  "target": "dynValue,6",
                  "prelabel": "Co-pay ",
                  "control": "select",
                  "type": "single",
                  "default": "EQ",
                  "optText": "=",
                  "altText": "EQ",
                  "optVal": "EQ",
                  "postlabel": "",
                  "jscall": "",
                  "lookup": ""
                },
                {
                  "id": "dsp.10.5.1.7",
                  "target": "dynValue,7",
                  "prelabel": "",
                  "control": "input",
                  "type": "text",
                  "default": "",
                  "postlabel": "% with",
                  "jscall": "onkeyup=isNumeric(this)",
                  "lookup": ""
                },
                {
                  "id": "dsp.10.5.1.8",
                  "target": "dynValue,8",
                  "prelabel": "Deductable amount",
                  "control": "select",
                  "type": "single",
                  "default": "EQ",
                  "optText": "=",
                  "altText": "EQ",
                  "optVal": "EQ",
                  "postlabel": "",
                  "jscall": "",
                  "lookup": ""
                },
                {
                  "id": "dsp.10.5.1.9",
                  "target": "dynValue,9",
                  "prelabel": "",
                  "control": "input",
                  "type": "text",
                  "default": "",
                  "postlabel": "",
                  "jscall": "onkeyup=isNumeric(this)",
                  "lookup": ""
                },
                {
                  "id": "dsp.10.5.1.10",
                  "target": "dynValue,10",
                  "prelabel": "",
                  "control": "input",
                  "type": "text",
                  "default": "OMR",
                  "optText": "",
                  "altText": "",
                  "optVal": "OMR",
                  "disabled": "true",
                  "postlabel": "",
                  "jscall": ""
                },
                {
                  "id": "dsp.10.5.1.11",
                  "target": "",
                  "prelabel": "",
                  "control": "image",
                  "type": "image",
                  "imagepath": "EditIcon.gif",
                  "alt": "Select Currency",
                  "default": "",
                  "postlabel": "",
                  "jscall": "onclick=openRadioList('dsp.10.5.1.10','CURRENCY_GROUP','option')"
                },
                {
                  "id": "dsp.10.5.1.12",
                  "target": "dynValue,11",
                  "prelabel": "<br>",
                  "control": "select",
                  "type": "single",
                  "default": "",
                  "optText": "MIN,MAX,BOTH",
                  "altText": "MIN,MAX,BOTH",
                  "optVal": "MIN,MAX,BOTH",
                  "postlabel": " ",
                  "jscall": ""
                },
                {
                  "id": "dsp.10.5.1.13",
                  "target": "dynValue,12",
                  "prelabel": "",
                  "control": "select",
                  "type": "single",
                  "default": "",
                  "optText": "Per Claim,Per Day,Per Policy Period",
                  "altText": "Per Claim,Per Day,Per Policy Period",
                  "optVal": "PC,PD,PP",
                  "postlabel": "",
                  "jscall": ""
                }
              ]
            },
            {
              "id": "cnd.10.5.2",
              "field": "gc2",
              "op": "",
              "opType": "",
              "value": "",
              "dynValue": "check_ip_op_limit('A|01999','~','~','~','~','~','~','~','~','~','~','~')",
              "clfactor": "10",
              "mandatory": "",
              "method": "get_request_state()",
              "source": "PACKAGE",
              "module": "P",
              "fieldData": "",
              "unit": "",
              "result": "",
              "configure": "NO",
              "display": [
                {
                  "id": "dsp.10.5.2.1",
                  "target": "dynValue,2",
                  "prelabel": "Anaesthesiology Limit amount",
                  "control": "select",
                  "type": "single",
                  "default": "LE",
                  "optText": "<=",
                  "altText": "LE",
                  "optVal": "LE",
                  "postlabel": "",
                  "jscall": "",
                  "lookup": ""
                },
                {
                  "id": "dsp.10.5.2.2",
                  "target": "dynValue,3",
                  "prelabel": "",
                  "control": "select",
                  "type": "single",
                  "default": "",
                  "optText": "fixed amount,% of Sum Insured",
                  "altText": "fixed amount,% of Sum Insured",
                  "optVal": "FA,SI",
                  "postlabel": "",
                  "jscall": ""
                },
                {
                  "id": "dsp.10.5.2.3",
                  "target": "dynValue,4",
                  "prelabel": "",
                  "control": "input",
                  "type": "text",
                  "default": "",
                  "postlabel": "",
                  "jscall": "onkeyup=isNumeric(this)",
                  "lookup": ""
                },
                {
                  "id": "dsp.10.5.2.4",
                  "target": "dynValue,5",
                  "prelabel": "",
                  "control": "input",
                  "type": "text",
                  "default": "OMR",
                  "optText": "",
                  "altText": "",
                  "optVal": "",
                  "disabled": "true",
                  "postlabel": "",
                  "jscall": ""
                },
                {
                  "id": "dsp.10.5.2.5",
                  "target": "",
                  "prelabel": "",
                  "control": "image",
                  "type": "image",
                  "imagepath": "EditIcon.gif",
                  "alt": "Select Currency",
                  "default": "",
                  "postlabel": "and",
                  "jscall": "onclick=openRadioList('dsp.10.5.2.4','CURRENCY_GROUP','option')"
                },
                {
                  "id": "dsp.10.5.2.6",
                  "target": "dynValue,6",
                  "prelabel": "Co-pay ",
                  "control": "select",
                  "type": "single",
                  "default": "EQ",
                  "optText": "=",
                  "altText": "EQ",
                  "optVal": "EQ",
                  "postlabel": "",
                  "jscall": "",
                  "lookup": ""
                },
                {
                  "id": "dsp.10.5.2.7",
                  "target": "dynValue,7",
                  "prelabel": "",
                  "control": "input",
                  "type": "text",
                  "default": "",
                  "postlabel": "% with",
                  "jscall": "onkeyup=isNumeric(this)",
                  "lookup": ""
                },
                {
                  "id": "dsp.10.5.2.8",
                  "target": "dynValue,8",
                  "prelabel": "Deductable amount",
                  "control": "select",
                  "type": "single",
                  "default": "EQ",
                  "optText": "=",
                  "altText": "EQ",
                  "optVal": "EQ",
                  "postlabel": "",
                  "jscall": "",
                  "lookup": ""
                },
                {
                  "id": "dsp.10.5.2.9",
                  "target": "dynValue,9",
                  "prelabel": "",
                  "control": "input",
                  "type": "text",
                  "default": "",
                  "postlabel": "",
                  "jscall": "onkeyup=isNumeric(this)",
                  "lookup": ""
                },
                {
                  "id": "dsp.10.5.2.10",
                  "target": "dynValue,10",
                  "prelabel": "",
                  "control": "input",
                  "type": "text",
                  "default": "OMR",
                  "optText": "",
                  "altText": "",
                  "optVal": "OMR",
                  "disabled": "true",
                  "postlabel": "",
                  "jscall": ""
                },
                {
                  "id": "dsp.10.5.2.11",
                  "target": "",
                  "prelabel": "",
                  "control": "image",
                  "type": "image",
                  "imagepath": "EditIcon.gif",
                  "alt": "Select Currency",
                  "default": "",
                  "postlabel": "",
                  "jscall": "onclick=openRadioList('dsp.10.5.2.10','CURRENCY_GROUP','option')"
                },
                {
                  "id": "dsp.10.5.2.12",
                  "target": "dynValue,11",
                  "prelabel": "<br>",
                  "control": "select",
                  "type": "single",
                  "default": "",
                  "optText": "MIN,MAX,BOTH",
                  "altText": "MIN,MAX,BOTH",
                  "optVal": "MIN,MAX,BOTH",
                  "postlabel": " ",
                  "jscall": ""
                },
                {
                  "id": "dsp.10.5.2.13",
                  "target": "dynValue,12",
                  "prelabel": "",
                  "control": "select",
                  "type": "single",
                  "default": "",
                  "optText": "Per Claim,Per Day,Per Policy Period",
                  "altText": "Per Claim,Per Day,Per Policy Period",
                  "optVal": "PC,PD,PP",
                  "postlabel": "",
                  "jscall": ""
                }
              ]
            },
            {
              "id": "cnd.10.5.3",
              "field": "gc2",
              "op": "",
              "opType": "",
              "value": "",
              "dynValue": "check_ip_op_limit('NOTGIVEN','~','~','~','~','~','~','~','~','~','~','~')",
              "clfactor": "10",
              "mandatory": "",
              "method": "get_request_state()",
              "source": "PACKAGE",
              "module": "P",
              "fieldData": "",
              "unit": "",
              "result": "",
              "configure": "NO",
              "display": [
                {
                  "id": "dsp.10.5.3.1",
                  "target": "dynValue,2",
                  "prelabel": "Surgeon's fees Limit amount",
                  "control": "select",
                  "type": "single",
                  "default": "LE",
                  "optText": "<=",
                  "altText": "LE",
                  "optVal": "LE",
                  "postlabel": "",
                  "jscall": "",
                  "lookup": ""
                },
                {
                  "id": "dsp.10.5.3.2",
                  "target": "dynValue,3",
                  "prelabel": "",
                  "control": "select",
                  "type": "single",
                  "default": "",
                  "optText": "fixed amount,% of Sum Insured",
                  "altText": "fixed amount,% of Sum Insured",
                  "optVal": "FA,SI",
                  "postlabel": "",
                  "jscall": ""
                },
                {
                  "id": "dsp.10.5.3.3",
                  "target": "dynValue,4",
                  "prelabel": "",
                  "control": "input",
                  "type": "text",
                  "default": "",
                  "postlabel": "",
                  "jscall": "onkeyup=isNumeric(this)",
                  "lookup": ""
                },
                {
                  "id": "dsp.10.5.3.4",
                  "target": "dynValue,5",
                  "prelabel": "",
                  "control": "input",
                  "type": "text",
                  "default": "OMR",
                  "optText": "",
                  "altText": "",
                  "optVal": "",
                  "disabled": "true",
                  "postlabel": "",
                  "jscall": ""
                },
                {
                  "id": "dsp.10.5.3.5",
                  "target": "",
                  "prelabel": "",
                  "control": "image",
                  "type": "image",
                  "imagepath": "EditIcon.gif",
                  "alt": "Select Currency",
                  "default": "",
                  "postlabel": "and",
                  "jscall": "onclick=openRadioList('dsp.10.5.3.4','CURRENCY_GROUP','option')"
                },
                {
                  "id": "dsp.10.5.3.6",
                  "target": "dynValue,6",
                  "prelabel": "Co-pay ",
                  "control": "select",
                  "type": "single",
                  "default": "EQ",
                  "optText": "=",
                  "altText": "EQ",
                  "optVal": "EQ",
                  "postlabel": "",
                  "jscall": "",
                  "lookup": ""
                },
                {
                  "id": "dsp.10.5.3.7",
                  "target": "dynValue,7",
                  "prelabel": "",
                  "control": "input",
                  "type": "text",
                  "default": "",
                  "postlabel": "% with",
                  "jscall": "onkeyup=isNumeric(this)",
                  "lookup": ""
                },
                {
                  "id": "dsp.10.5.3.8",
                  "target": "dynValue,8",
                  "prelabel": "Deductable amount",
                  "control": "select",
                  "type": "single",
                  "default": "EQ",
                  "optText": "=",
                  "altText": "EQ",
                  "optVal": "EQ",
                  "postlabel": "",
                  "jscall": "",
                  "lookup": ""
                },
                {
                  "id": "dsp.10.5.3.9",
                  "target": "dynValue,9",
                  "prelabel": "",
                  "control": "input",
                  "type": "text",
                  "default": "",
                  "postlabel": "",
                  "jscall": "onkeyup=isNumeric(this)",
                  "lookup": ""
                },
                {
                  "id": "dsp.10.5.3.10",
                  "target": "dynValue,10",
                  "prelabel": "",
                  "control": "input",
                  "type": "text",
                  "default": "OMR",
                  "optText": "",
                  "altText": "",
                  "optVal": "OMR",
                  "disabled": "true",
                  "postlabel": "",
                  "jscall": ""
                },
                {
                  "id": "dsp.10.5.3.11",
                  "target": "",
                  "prelabel": "",
                  "control": "image",
                  "type": "image",
                  "imagepath": "EditIcon.gif",
                  "alt": "Select Currency",
                  "default": "",
                  "postlabel": "",
                  "jscall": "onclick=openRadioList('dsp.10.5.3.10','CURRENCY_GROUP','option')"
                },
                {
                  "id": "dsp.10.5.3.12",
                  "target": "dynValue,11",
                  "prelabel": "<br>",
                  "control": "select",
                  "type": "single",
                  "default": "",
                  "optText": "MIN,MAX,BOTH",
                  "altText": "MIN,MAX,BOTH",
                  "optVal": "MIN,MAX,BOTH",
                  "postlabel": " ",
                  "jscall": ""
                },
                {
                  "id": "dsp.10.5.3.13",
                  "target": "dynValue,12",
                  "prelabel": "",
                  "control": "select",
                  "type": "single",
                  "default": "",
                  "optText": "Per Claim,Per Day,Per Policy Period",
                  "altText": "Per Claim,Per Day,Per Policy Period",
                  "optVal": "PC,PD,PP",
                  "postlabel": "",
                  "jscall": ""
                }
              ]
            }
          ]
        }
      ]
    },
    {
      "id": "cls.15",
      "name": "Chronic Condition & Pre-Exising Condition",
      "allowed": "NO",
      "type": "rule",
      "execution": "PRE,CLA",
      "coverage": [
        {
          "id": "cvg.15.1",
          "name": "Rule Applicable for Combined Pre-Exising & Chronic Condition",
          "allowed": "~",
          "module": "P",
          "clpercentage": "",
          "selected": "YES",
          "autoselect": "",
          "display": {
            "id": "dsp.15.1.1",
            "target": "allowed,1",
            "prelabel": "",
            "control": "radiogroup",
            "type": "single",
            "default": "2",
            "optText": "Pay,Don't Pay,Pay Conditionally",
            "altText": "Pay,Don't Pay,Pay Conditionally",
            "optVal": "1,2,3",
            "postlabel": "",
            "jscall": "onclick=showHideCondition(this)"
          },
          "condition": [
            {
              "id": "cnd.15.1.0",
              "field": "",
              "op": "",
              "opType": "",
              "value": "",
              "clfactor": "10",
              "mandatory": "NO",
              "method": "",
              "dynValue": "get_chronic_mem_waiting_prd('ICD001','~','~','~')",
              "source": "PACKAGE",
              "module": "P",
              "fieldData": "",
              "unit": "",
              "result": "",
              "display": [
                {
                  "id": "dsp.15.1.0.1",
                  "target": "dynValue,2",
                  "prelabel": "Waiting Period",
                  "control": "select",
                  "type": "single",
                  "default": "GE",
                  "optText": ">=",
                  "altText": ">=",
                  "optVal": "GE",
                  "postlabel": "",
                  "jscall": ""
                },
                {
                  "id": "dsp.15.1.0.2",
                  "target": "dynValue,3",
                  "prelabel": "",
                  "control": "input",
                  "type": "text",
                  "default": "",
                  "optText": "",
                  "altText": "",
                  "optVal": "",
                  "disabled": "",
                  "postlabel": "",
                  "jscall": "onkeyup=isNumeric(this)"
                },
                {
                  "id": "dsp.15.1.0.3",
                  "target": "dynValue,4",
                  "prelabel": "",
                  "control": "select",
                  "type": "single",
                  "default": "",
                  "optText": "days,months,years",
                  "altText": "days,months,years",
                  "optVal": "DD,MM,YY",
                  "postlabel": "from the member policy Inception Date",
                  "jscall": ""
                }
              ]
            },
            {
              "id": "cnd.15.1.1",
              "field": "oc1",
              "op": "",
              "opType": "",
              "value": "",
              "dynValue": "check_authorization('NOTGIVEN','~')",
              "clfactor": "10",
              "mandatory": "NO",
              "method": "get_request_state()",
              "source": "PACKAGE",
              "module": "P",
              "fieldData": "",
              "unit": "",
              "result": "",
              "configure": "NO",
              "display": {
                "id": "dsp.15.1.1.1",
                "target": "dynValue,2",
                "prelabel": "Authorization  required",
                "control": "select",
                "type": "text",
                "disabled": "",
                "default": "Y",
                "optText": "Yes,No",
                "altText": "Yes,No",
                "optVal": "Y,N",
                "postlabel": "",
                "jscall": "",
                "lookup": ""
              }
            },
            {
              "id": "cnd.15.1.2",
              "field": "oc1",
              "op": "",
              "opType": "",
              "value": "",
              "dynValue": "Update_Rule_Limit_App_Flag('ICD001','~')",
              "clfactor": "10",
              "mandatory": "NO",
              "method": "get_request_state()",
              "source": "PACKAGE",
              "module": "P",
              "fieldData": "",
              "unit": "",
              "result": "",
              "configure": "NO",
              "display": {
                "id": "dsp.15.1.2.1",
                "target": "dynValue,2",
                "prelabel": "Limit applicable",
                "control": "select",
                "type": "text",
                "disabled": "",
                "default": "OCL",
                "optText": "Within Combined PED & CC  Limit,Within OP/IP Limit",
                "altText": "Within Combined PED & CC  Limit Limit,Within OP/IP Limit",
                "optVal": "WCL,WOP",
                "postlabel": "",
                "lookup": ""
              }
            },
            {
              "id": "cnd.15.1.3",
              "field": "assistance.cover1",
              "value": "",
              "dynValue": "check_chronic_ped_combo_limit('ICD001','~','~','~','~','~','~','~','~','~','~','~','~','~','~')",
              "clfactor": "10",
              "mandatory": "NO",
              "method": "get_request_country()",
              "source": "PACKAGE",
              "module": "P",
              "fieldData": "",
              "unit": "",
              "result": "",
              "configure": "NO",
              "display": [
                {
                  "id": "dsp.15.1.3.1",
                  "target": "dynValue,2",
                  "prelabel": "<span id='chr15'>Overall Combined PED & CC Limit Amount",
                  "control": "select",
                  "type": "single",
                  "default": "LE",
                  "optText": "<=",
                  "altText": "LE",
                  "optVal": "LE",
                  "postlabel": "",
                  "jscall": "",
                  "lookup": ""
                },
                {
                  "id": "dsp.15.1.3.2",
                  "target": "dynValue,3",
                  "prelabel": "",
                  "control": "select",
                  "type": "single",
                  "default": "",
                  "optText": "fixed amount,% of Sum Insured",
                  "altText": "fixed amount,% of Sum Insured",
                  "optVal": "FA,SI",
                  "postlabel": "",
                  "jscall": ""
                },
                {
                  "id": "dsp.15.1.3.3",
                  "target": "dynValue,4",
                  "prelabel": "",
                  "control": "input",
                  "type": "text",
                  "default": "",
                  "postlabel": "",
                  "jscall": "onkeyup=isNumeric(this)",
                  "lookup": ""
                },
                {
                  "id": "dsp.15.1.3.4",
                  "target": "dynValue,5",
                  "prelabel": "",
                  "control": "input",
                  "type": "text",
                  "default": "OMR",
                  "optText": "",
                  "altText": "",
                  "optVal": "",
                  "disabled": "true",
                  "postlabel": "",
                  "jscall": ""
                },
                {
                  "id": "dsp.15.1.3.6",
                  "target": "dynValue,6",
                  "prelabel": "and Co-pay",
                  "control": "select",
                  "type": "single",
                  "default": "EQ",
                  "optText": "=",
                  "altText": "EQ",
                  "optVal": "EQ",
                  "postlabel": "",
                  "jscall": "",
                  "lookup": ""
                },
                {
                  "id": "dsp.15.1.3.7",
                  "target": "dynValue,7",
                  "prelabel": "",
                  "control": "input",
                  "type": "text",
                  "default": "",
                  "postlabel": "%",
                  "jscall": "onkeyup=isNumeric(this)",
                  "lookup": ""
                },
                {
                  "id": "dsp.15.1.3.8",
                  "target": "dynValue,8",
                  "prelabel": "with Deductable amount",
                  "control": "select",
                  "type": "single",
                  "default": "EQ",
                  "optText": "=",
                  "altText": "EQ",
                  "optVal": "EQ",
                  "postlabel": "",
                  "jscall": "",
                  "lookup": ""
                },
                {
                  "id": "dsp.15.1.3.9",
                  "target": "dynValue,9",
                  "prelabel": "",
                  "control": "input",
                  "type": "text",
                  "default": "",
                  "postlabel": "",
                  "jscall": "onkeyup=isNumeric(this)",
                  "lookup": ""
                },
                {
                  "id": "dsp.15.1.3.10",
                  "target": "dynValue,10",
                  "prelabel": "",
                  "control": "input",
                  "type": "text",
                  "default": "OMR",
                  "optText": "",
                  "altText": "",
                  "optVal": "OMR",
                  "disabled": "true",
                  "postlabel": "",
                  "jscall": ""
                },
                {
                  "id": "dsp.15.1.3.11",
                  "target": "",
                  "prelabel": "",
                  "control": "image",
                  "type": "image",
                  "imagepath": "EditIcon.gif",
                  "alt": "Select Currency",
                  "default": "",
                  "postlabel": "",
                  "jscall": "onclick=openRadioList('dsp.15.1.3.11','CURRENCY_GROUP','option')"
                },
                {
                  "id": "dsp.15.1.3.12",
                  "target": "dynValue,11",
                  "prelabel": "",
                  "control": "select",
                  "type": "single",
                  "default": "MIN",
                  "optText": "MIN,MAX,BOTH",
                  "altText": "MIN,MAX,BOTH",
                  "optVal": "MIN,MAX,BOTH",
                  "postlabel": "",
                  "jscall": ""
                },
                {
                  "id": "dsp.15.1.3.19",
                  "target": "dynValue,12",
                  "prelabel": "with max copayment",
                  "control": "input",
                  "type": "text",
                  "default": "",
                  "postlabel": "",
                  "jscall": "onkeyup=isNumeric(this)",
                  "lookup": ""
                },
                {
                  "id": "dsp.15.1.3.20",
                  "target": "dynValue,13",
                  "prelabel": "",
                  "control": "input",
                  "type": "text",
                  "default": "OMR",
                  "optText": "",
                  "altText": "",
                  "optVal": "OMR",
                  "disabled": "true",
                  "postlabel": "",
                  "jscall": ""
                },
                {
                  "id": "dsp.15.1.3.21",
                  "target": "",
                  "prelabel": "",
                  "control": "image",
                  "type": "image",
                  "imagepath": "EditIcon.gif",
                  "alt": "Select Currency",
                  "default": "",
                  "postlabel": "per claim",
                  "jscall": "onclick=openRadioList('dsp.15.1.3.20','CURRENCY_GROUP','option')"
                },
                {
                  "id": "dsp.15.1.3.19",
                  "target": "dynValue,14",
                  "prelabel": "max copayment",
                  "control": "input",
                  "type": "text",
                  "default": "",
                  "postlabel": "",
                  "jscall": "onkeyup=isNumeric(this)",
                  "lookup": ""
                },
                {
                  "id": "dsp.15.1.3.20",
                  "target": "dynValue,15",
                  "prelabel": "",
                  "control": "input",
                  "type": "text",
                  "default": "OMR",
                  "optText": "",
                  "altText": "",
                  "optVal": "OMR",
                  "disabled": "true",
                  "postlabel": "",
                  "jscall": ""
                },
                {
                  "id": "dsp.15.1.3.21",
                  "target": "",
                  "prelabel": "",
                  "control": "image",
                  "type": "image",
                  "imagepath": "EditIcon.gif",
                  "alt": "Select Currency",
                  "default": "",
                  "postlabel": "per policy",
                  "jscall": "onclick=openRadioList('dsp.15.1.3.20','CURRENCY_GROUP','option')"
                }
              ]
            },
            {
              "id": "cnd.15.1.4",
              "field": "assistance.cover1",
              "value": "",
              "dynValue": "check_op_combined_limit('ICD001','~','~','~','~','~','~','~','~','~','~','~')",
              "clfactor": "10",
              "mandatory": "NO",
              "method": "get_request_country()",
              "source": "PACKAGE",
              "module": "P",
              "fieldData": "",
              "unit": "",
              "result": "",
              "configure": "NO",
              "display": [
                {
                  "id": "dsp.15.1.4.1",
                  "target": "dynValue,2",
                  "prelabel": "<span id='chr16'>OP Combined PED & CC Limit Amount",
                  "control": "select",
                  "type": "single",
                  "default": "LE",
                  "optText": "<=",
                  "altText": "LE",
                  "optVal": "LE",
                  "postlabel": "",
                  "jscall": "",
                  "lookup": ""
                },
                {
                  "id": "dsp.15.1.4.2",
                  "target": "dynValue,3",
                  "prelabel": "",
                  "control": "select",
                  "type": "single",
                  "default": "",
                  "optText": "fixed amount,% of Sum Insured",
                  "altText": "fixed amount,% of Sum Insured",
                  "optVal": "FA,SI",
                  "postlabel": "",
                  "jscall": ""
                },
                {
                  "id": "dsp.15.1.4.3",
                  "target": "dynValue,4",
                  "prelabel": "",
                  "control": "input",
                  "type": "text",
                  "default": "",
                  "postlabel": "",
                  "jscall": "onkeyup=isNumeric(this)",
                  "lookup": ""
                },
                {
                  "id": "dsp.15.1.4.4",
                  "target": "dynValue,5",
                  "prelabel": "",
                  "control": "input",
                  "type": "text",
                  "default": "OMR",
                  "optText": "",
                  "altText": "",
                  "optVal": "",
                  "disabled": "true",
                  "postlabel": "",
                  "jscall": ""
                },
                {
                  "id": "dsp.15.1.4.6",
                  "target": "dynValue,6",
                  "prelabel": "and Co-pay",
                  "control": "select",
                  "type": "single",
                  "default": "EQ",
                  "optText": "=",
                  "altText": "EQ",
                  "optVal": "EQ",
                  "postlabel": "",
                  "jscall": "",
                  "lookup": ""
                },
                {
                  "id": "dsp.15.1.4.7",
                  "target": "dynValue,7",
                  "prelabel": "",
                  "control": "input",
                  "type": "text",
                  "default": "",
                  "postlabel": "%",
                  "jscall": "onkeyup=isNumeric(this)",
                  "lookup": ""
                },
                {
                  "id": "dsp.15.1.4.8",
                  "target": "dynValue,8",
                  "prelabel": "with Deductable amount",
                  "control": "select",
                  "type": "single",
                  "default": "EQ",
                  "optText": "=",
                  "altText": "EQ",
                  "optVal": "EQ",
                  "postlabel": "",
                  "jscall": "",
                  "lookup": ""
                },
                {
                  "id": "dsp.15.1.4.9",
                  "target": "dynValue,9",
                  "prelabel": "",
                  "control": "input",
                  "type": "text",
                  "default": "",
                  "postlabel": "",
                  "jscall": "onkeyup=isNumeric(this)",
                  "lookup": ""
                },
                {
                  "id": "dsp.15.1.4.10",
                  "target": "dynValue,10",
                  "prelabel": "",
                  "control": "input",
                  "type": "text",
                  "default": "OMR",
                  "optText": "",
                  "altText": "",
                  "optVal": "OMR",
                  "disabled": "true",
                  "postlabel": "",
                  "jscall": ""
                },
                {
                  "id": "dsp.15.1.4.11",
                  "target": "",
                  "prelabel": "",
                  "control": "image",
                  "type": "image",
                  "imagepath": "EditIcon.gif",
                  "alt": "Select Currency",
                  "default": "",
                  "postlabel": "",
                  "jscall": "onclick=openRadioList('dsp.15.1.4.10','CURRENCY_GROUP','option')"
                },
                {
                  "id": "dsp.15.1.4.12",
                  "target": "dynValue,11",
                  "prelabel": "",
                  "control": "select",
                  "type": "single",
                  "default": "MIN",
                  "optText": "MIN,MAX,BOTH",
                  "altText": "MIN,MAX,BOTH",
                  "optVal": "MIN,MAX,BOTH",
                  "postlabel": "",
                  "jscall": ""
                },
                {
                  "id": "dsp.15.1.4.13",
                  "target": "dynValue,12",
                  "prelabel": "",
                  "control": "select",
                  "type": "single",
                  "default": "Per Claim",
                  "optText": "Per Claim,Per Policy Period",
                  "altText": "Per Claim,Per Policy Period",
                  "optVal": "PC,PP",
                  "postlabel": "",
                  "jscall": ""
                }
              ]
            },
            {
              "id": "cnd.15.1.5",
              "field": "assistance.cover1",
              "value": "",
              "dynValue": "check_ip_combined_limit('ICD001','~','~','~','~','~','~','~','~','~','~','~')",
              "clfactor": "10",
              "mandatory": "NO",
              "method": "get_request_country()",
              "source": "PACKAGE",
              "module": "P",
              "fieldData": "",
              "unit": "",
              "result": "",
              "configure": "NO",
              "display": [
                {
                  "id": "dsp.15.1.5.1",
                  "target": "dynValue,2",
                  "prelabel": "<span id='chr17'>IP Combined PED & CC Limit",
                  "control": "select",
                  "type": "single",
                  "default": "LE",
                  "optText": "<=",
                  "altText": "LE",
                  "optVal": "LE",
                  "postlabel": "",
                  "jscall": "",
                  "lookup": ""
                },
                {
                  "id": "dsp.15.1.5.2",
                  "target": "dynValue,3",
                  "prelabel": "",
                  "control": "select",
                  "type": "single",
                  "default": "",
                  "optText": "fixed amount,% of Sum Insured",
                  "altText": "fixed amount,% of Sum Insured",
                  "optVal": "FA,SI",
                  "postlabel": "",
                  "jscall": ""
                },
                {
                  "id": "dsp.15.1.5.3",
                  "target": "dynValue,4",
                  "prelabel": "",
                  "control": "input",
                  "type": "text",
                  "default": "",
                  "postlabel": "",
                  "jscall": "onkeyup=isNumeric(this)",
                  "lookup": ""
                },
                {
                  "id": "dsp.15.1.5.4",
                  "target": "dynValue,5",
                  "prelabel": "",
                  "control": "input",
                  "type": "text",
                  "default": "OMR",
                  "optText": "",
                  "altText": "",
                  "optVal": "",
                  "disabled": "true",
                  "postlabel": "",
                  "jscall": ""
                },
                {
                  "id": "dsp.15.1.5.6",
                  "target": "dynValue,6",
                  "prelabel": "and Co-pay",
                  "control": "select",
                  "type": "single",
                  "default": "EQ",
                  "optText": "=",
                  "altText": "EQ",
                  "optVal": "EQ",
                  "postlabel": "",
                  "jscall": "",
                  "lookup": ""
                },
                {
                  "id": "dsp.15.1.5.7",
                  "target": "dynValue,7",
                  "prelabel": "",
                  "control": "input",
                  "type": "text",
                  "default": "",
                  "postlabel": "%",
                  "jscall": "onkeyup=isNumeric(this)",
                  "lookup": ""
                },
                {
                  "id": "dsp.15.1.5.8",
                  "target": "dynValue,8",
                  "prelabel": "with Deductable amount",
                  "control": "select",
                  "type": "single",
                  "default": "EQ",
                  "optText": "=",
                  "altText": "EQ",
                  "optVal": "EQ",
                  "postlabel": "",
                  "jscall": "",
                  "lookup": ""
                },
                {
                  "id": "dsp.15.1.5.9",
                  "target": "dynValue,9",
                  "prelabel": "",
                  "control": "input",
                  "type": "text",
                  "default": "",
                  "postlabel": "",
                  "jscall": "onkeyup=isNumeric(this)",
                  "lookup": ""
                },
                {
                  "id": "dsp.15.1.5.10",
                  "target": "dynValue,10",
                  "prelabel": "",
                  "control": "input",
                  "type": "text",
                  "default": "OMR",
                  "optText": "",
                  "altText": "",
                  "optVal": "OMR",
                  "disabled": "true",
                  "postlabel": "",
                  "jscall": ""
                },
                {
                  "id": "dsp.15.1.5.11",
                  "target": "",
                  "prelabel": "",
                  "control": "image",
                  "type": "image",
                  "imagepath": "EditIcon.gif",
                  "alt": "Select Currency",
                  "default": "",
                  "postlabel": "",
                  "jscall": "onclick=openRadioList('dsp.15.1.5.10','CURRENCY_GROUP','option')"
                },
                {
                  "id": "dsp.15.1.5.12",
                  "target": "dynValue,11",
                  "prelabel": "",
                  "control": "select",
                  "type": "single",
                  "default": "MIN",
                  "optText": "MIN,MAX,BOTH",
                  "altText": "MIN,MAX,BOTH",
                  "optVal": "MIN,MAX,BOTH",
                  "postlabel": "",
                  "jscall": ""
                },
                {
                  "id": "dsp.15.1.5.13",
                  "target": "dynValue,12",
                  "prelabel": "",
                  "control": "select",
                  "type": "single",
                  "default": "Per Claim",
                  "optText": "Per Claim,Per Policy Period",
                  "altText": "Per Claim,Per Policy Period",
                  "optVal": "PC,PP",
                  "postlabel": "",
                  "jscall": ""
                }
              ]
            }
          ],
          "action": {
            "id": "act.15.1.1",
            "name": "Chronic PED Combined"
          }
        },
        {
          "id": "cvg.15.3",
          "name": "Rule Applicable for Chronic Condition",
          "allowed": "~",
          "module": "P",
          "clpercentage": "",
          "selected": "YES",
          "autoselect": "",
          "display": {
            "id": "dsp.15.3.1",
            "target": "allowed,1",
            "prelabel": "",
            "control": "radiogroup",
            "type": "single",
            "default": "2",
            "optText": "Pay,Don't Pay,Pay Conditionally",
            "altText": "Pay,Don't Pay,Pay Conditionally",
            "optVal": "1,2,3",
            "postlabel": "",
            "jscall": "onclick=showHideCondition(this)"
          },
          "condition": [
            {
              "id": "cnd.15.3.6",
              "field": "assistance.cover1",
              "value": "",
              "dynValue": "check_acute_chronic_limit('ICD001','~','~','~','~')",
              "cclfactor": "10",
              "mandatory": "NO",
              "method": "get_request_country()",
              "source": "PACKAGE",
              "module": "P",
              "fieldData": "",
              "unit": "",
              "result": "",
              "configure": "NO",
              "display": [
                {
                  "id": "dsp.15.3.6.1",
                  "target": "dynValue,2",
                  "prelabel": "Acute Phase Treatment for Chronic Condition",
                  "control": "select",
                  "type": "text",
                  "disabled": "",
                  "default": "Y",
                  "optText": "Covered,Not Covered",
                  "altText": "Covered,Not Covered",
                  "optVal": "Y,N",
                  "postlabel": "",
                  "jscall": "",
                  "lookup": ""
                },
                {
                  "id": "dsp.15.3.6.2",
                  "target": "dynValue,3",
                  "prelabel": "Limit",
                  "control": "select",
                  "type": "single",
                  "default": "GE",
                  "optText": ">=",
                  "altText": ">=",
                  "optVal": "GE",
                  "postlabel": "",
                  "jscall": ""
                },
                {
                  "id": "dsp.15.3.6.3",
                  "target": "dynValue,4",
                  "prelabel": "",
                  "control": "input",
                  "type": "text",
                  "default": "",
                  "optText": "",
                  "altText": "",
                  "optVal": "",
                  "disabled": "",
                  "postlabel": "",
                  "jscall": "onkeyup=isNumeric(this)"
                },
                {
                  "id": "dsp.15.3.6.4",
                  "target": "dynValue,5",
                  "prelabel": "",
                  "control": "input",
                  "type": "text",
                  "default": "OMR",
                  "optText": "",
                  "altText": "",
                  "optVal": "",
                  "disabled": "true",
                  "postlabel": "",
                  "jscall": ""
                }
              ]
            },
            {
              "id": "cnd.15.3.0",
              "field": "",
              "op": "",
              "opType": "",
              "value": "",
              "clfactor": "10",
              "mandatory": "NO",
              "method": "",
              "dynValue": "get_chronic_mem_waiting_prd('ICD001','~','~','~')",
              "source": "PACKAGE",
              "module": "P",
              "fieldData": "",
              "unit": "",
              "result": "",
              "display": [
                {
                  "id": "dsp.15.3.0.1",
                  "target": "dynValue,2",
                  "prelabel": "Waiting Period",
                  "control": "select",
                  "type": "single",
                  "default": "GE",
                  "optText": ">=",
                  "altText": ">=",
                  "optVal": "GE",
                  "postlabel": "",
                  "jscall": ""
                },
                {
                  "id": "dsp.15.3.0.2",
                  "target": "dynValue,3",
                  "prelabel": "",
                  "control": "input",
                  "type": "text",
                  "default": "",
                  "optText": "",
                  "altText": "",
                  "optVal": "",
                  "disabled": "",
                  "postlabel": "",
                  "jscall": "onkeyup=isNumeric(this)"
                },
                {
                  "id": "dsp.15.3.0.3",
                  "target": "dynValue,4",
                  "prelabel": "",
                  "control": "select",
                  "type": "single",
                  "default": "",
                  "optText": "days,months,years",
                  "altText": "days,months,years",
                  "optVal": "DD,MM,YY",
                  "postlabel": "from the member policy Inception Date",
                  "jscall": ""
                }
              ]
            },
            {
              "id": "cnd.15.3.1",
              "field": "oc1",
              "op": "",
              "opType": "",
              "value": "",
              "dynValue": "check_authorization('NOTGIVEN','~')",
              "clfactor": "10",
              "mandatory": "NO",
              "method": "get_request_state()",
              "source": "PACKAGE",
              "module": "P",
              "fieldData": "",
              "unit": "",
              "result": "",
              "configure": "NO",
              "display": {
                "id": "dsp.15.3.1.1",
                "target": "dynValue,2",
                "prelabel": "Authorization  required",
                "control": "select",
                "type": "text",
                "disabled": "",
                "default": "Y",
                "optText": "Yes,No",
                "altText": "Yes,No",
                "optVal": "Y,N",
                "postlabel": "",
                "jscall": "",
                "lookup": ""
              }
            },
            {
              "id": "cnd.15.3.2",
              "field": "oc1",
              "op": "",
              "opType": "",
              "value": "",
              "dynValue": "Update_Rule_Limit_App_Flag('ICD001','~')",
              "clfactor": "10",
              "mandatory": "NO",
              "method": "get_request_state()",
              "source": "PACKAGE",
              "module": "P",
              "fieldData": "",
              "unit": "",
              "result": "",
              "configure": "NO",
              "display": {
                "id": "dsp.15.3.2.1",
                "target": "dynValue,2",
                "prelabel": "Limit applicable",
                "control": "select",
                "type": "text",
                "disabled": "",
                "default": "OCL",
                "optText": "Within Chronic Condition Limit,Within OP/IP Limit",
                "altText": "Within Chronic Condition Limit,Within OP/IP Limit,",
                "optVal": "OCL,WOP",
                "postlabel": "",
                "lookup": ""
              }
            },
            {
              "id": "cnd.15.3.3",
              "field": "assistance.cover1",
              "value": "",
              "dynValue": "check_chronic_limit('ICD001','~','~','~','~','~','~','~','~','~','~','~')",
              "clfactor": "10",
              "mandatory": "NO",
              "method": "get_request_country()",
              "source": "PACKAGE",
              "module": "P",
              "fieldData": "",
              "unit": "",
              "result": "",
              "configure": "NO",
              "display": [
                {
                  "id": "dsp.15.3.3.1",
                  "target": "dynValue,2",
                  "prelabel": "<span id='chr21'>Overall Chronic Condition Limit",
                  "control": "select",
                  "type": "single",
                  "default": "LE",
                  "optText": "<=",
                  "altText": "LE",
                  "optVal": "LE",
                  "postlabel": "",
                  "jscall": "",
                  "lookup": ""
                },
                {
                  "id": "dsp.15.3.3.2",
                  "target": "dynValue,3",
                  "prelabel": "",
                  "control": "select",
                  "type": "single",
                  "default": "",
                  "optText": "fixed amount,% of Sum Insured",
                  "altText": "fixed amount,% of Sum Insured",
                  "optVal": "FA,SI",
                  "postlabel": "",
                  "jscall": ""
                },
                {
                  "id": "dsp.15.3.3.3",
                  "target": "dynValue,4",
                  "prelabel": "",
                  "control": "input",
                  "type": "text",
                  "default": "",
                  "postlabel": "",
                  "jscall": "onkeyup=isNumeric(this)",
                  "lookup": ""
                },
                {
                  "id": "dsp.15.3.3.4",
                  "target": "dynValue,5",
                  "prelabel": "",
                  "control": "input",
                  "type": "text",
                  "default": "OMR",
                  "optText": "",
                  "altText": "",
                  "optVal": "",
                  "disabled": "true",
                  "postlabel": "",
                  "jscall": ""
                },
                {
                  "id": "dsp.15.3.3.6",
                  "target": "dynValue,6",
                  "prelabel": "and Co-pay",
                  "control": "select",
                  "type": "single",
                  "default": "EQ",
                  "optText": "=",
                  "altText": "EQ",
                  "optVal": "EQ",
                  "postlabel": "",
                  "jscall": "",
                  "lookup": ""
                },
                {
                  "id": "dsp.15.3.3.7",
                  "target": "dynValue,7",
                  "prelabel": "",
                  "control": "input",
                  "type": "text",
                  "default": "",
                  "postlabel": "%",
                  "jscall": "onkeyup=isNumeric(this)",
                  "lookup": ""
                },
                {
                  "id": "dsp.15.3.3.8",
                  "target": "dynValue,8",
                  "prelabel": "with Deductable amount",
                  "control": "select",
                  "type": "single",
                  "default": "EQ",
                  "optText": "=",
                  "altText": "EQ",
                  "optVal": "EQ",
                  "postlabel": "",
                  "jscall": "",
                  "lookup": ""
                },
                {
                  "id": "dsp.15.3.3.9",
                  "target": "dynValue,9",
                  "prelabel": "",
                  "control": "input",
                  "type": "text",
                  "default": "",
                  "postlabel": "",
                  "jscall": "onkeyup=isNumeric(this)",
                  "lookup": ""
                },
                {
                  "id": "dsp.15.3.3.10",
                  "target": "dynValue,10",
                  "prelabel": "",
                  "control": "input",
                  "type": "text",
                  "default": "OMR",
                  "optText": "",
                  "altText": "",
                  "optVal": "OMR",
                  "disabled": "true",
                  "postlabel": "",
                  "jscall": ""
                },
                {
                  "id": "dsp.15.3.3.11",
                  "target": "",
                  "prelabel": "",
                  "control": "image",
                  "type": "image",
                  "imagepath": "EditIcon.gif",
                  "alt": "Select Currency",
                  "default": "",
                  "postlabel": "",
                  "jscall": "onclick=openRadioList('dsp.10.1.1.12','CURRENCY_GROUP','option')"
                },
                {
                  "id": "dsp.15.3.3.12",
                  "target": "dynValue,11",
                  "prelabel": "",
                  "control": "select",
                  "type": "single",
                  "default": "MIN",
                  "optText": "MIN,MAX,BOTH",
                  "altText": "MIN,MAX,BOTH",
                  "optVal": "MIN,MAX,BOTH",
                  "postlabel": "",
                  "jscall": ""
                },
                {
                  "id": "dsp.15.3.3.13",
                  "target": "dynValue,12",
                  "prelabel": "",
                  "control": "select",
                  "type": "single",
                  "default": "",
                  "optText": "Per Claim,Per Policy Period",
                  "altText": "Per Claim,Per Policy Period",
                  "optVal": "PC,PP",
                  "postlabel": "",
                  "jscall": ""
                }
              ]
            },
            {
              "id": "cnd.15.3.4",
              "field": "assistance.cover1",
              "value": "",
              "dynValue": "check_op_chronic_limit('ICD001','~','~','~','~','~','~','~','~','~','~','~')",
              "clfactor": "10",
              "mandatory": "NO",
              "method": "get_request_country()",
              "source": "PACKAGE",
              "module": "P",
              "fieldData": "",
              "unit": "",
              "result": "",
              "configure": "NO",
              "display": [
                {
                  "id": "dsp.15.3.4.1",
                  "target": "dynValue,2",
                  "prelabel": "<span id='chr22'>OP Chronic Condition Limit",
                  "control": "select",
                  "type": "single",
                  "default": "LE",
                  "optText": "<=",
                  "altText": "LE",
                  "optVal": "LE",
                  "postlabel": "",
                  "jscall": "",
                  "lookup": ""
                },
                {
                  "id": "dsp.15.3.4.2",
                  "target": "dynValue,3",
                  "prelabel": "",
                  "control": "select",
                  "type": "single",
                  "default": "",
                  "optText": "fixed amount,% of Sum Insured",
                  "altText": "fixed amount,% of Sum Insured",
                  "optVal": "FA,SI",
                  "postlabel": "",
                  "jscall": ""
                },
                {
                  "id": "dsp.15.3.4.3",
                  "target": "dynValue,4",
                  "prelabel": "",
                  "control": "input",
                  "type": "text",
                  "default": "",
                  "postlabel": "",
                  "jscall": "onkeyup=isNumeric(this)",
                  "lookup": ""
                },
                {
                  "id": "dsp.15.3.4.4",
                  "target": "dynValue,5",
                  "prelabel": "",
                  "control": "input",
                  "type": "text",
                  "default": "OMR",
                  "optText": "",
                  "altText": "",
                  "optVal": "",
                  "disabled": "true",
                  "postlabel": "",
                  "jscall": ""
                },
                {
                  "id": "dsp.15.3.4.6",
                  "target": "dynValue,6",
                  "prelabel": "and Co-pay",
                  "control": "select",
                  "type": "single",
                  "default": "EQ",
                  "optText": "=",
                  "altText": "EQ",
                  "optVal": "EQ",
                  "postlabel": "",
                  "jscall": "",
                  "lookup": ""
                },
                {
                  "id": "dsp.15.3.4.7",
                  "target": "dynValue,7",
                  "prelabel": "",
                  "control": "input",
                  "type": "text",
                  "default": "",
                  "postlabel": "%",
                  "jscall": "onkeyup=isNumeric(this)",
                  "lookup": ""
                },
                {
                  "id": "dsp.15.3.4.8",
                  "target": "dynValue,8",
                  "prelabel": "with Deductable amount",
                  "control": "select",
                  "type": "single",
                  "default": "EQ",
                  "optText": "=",
                  "altText": "EQ",
                  "optVal": "EQ",
                  "postlabel": "",
                  "jscall": "",
                  "lookup": ""
                },
                {
                  "id": "dsp.15.3.4.9",
                  "target": "dynValue,9",
                  "prelabel": "",
                  "control": "input",
                  "type": "text",
                  "default": "",
                  "postlabel": "",
                  "jscall": "onkeyup=isNumeric(this)",
                  "lookup": ""
                },
                {
                  "id": "dsp.15.3.4.10",
                  "target": "dynValue,10",
                  "prelabel": "",
                  "control": "input",
                  "type": "text",
                  "default": "OMR",
                  "optText": "",
                  "altText": "",
                  "optVal": "OMR",
                  "disabled": "true",
                  "postlabel": "",
                  "jscall": ""
                },
                {
                  "id": "dsp.15.3.4.11",
                  "target": "",
                  "prelabel": "",
                  "control": "image",
                  "type": "image",
                  "imagepath": "EditIcon.gif",
                  "alt": "Select Currency",
                  "default": "",
                  "postlabel": "",
                  "jscall": "onclick=openRadioList('dsp.15.3.4.11','CURRENCY_GROUP','option')"
                },
                {
                  "id": "dsp.15.3.4.12",
                  "target": "dynValue,11",
                  "prelabel": "",
                  "control": "select",
                  "type": "single",
                  "default": "MIN",
                  "optText": "MIN,MAX,BOTH",
                  "altText": "MIN,MAX,BOTH",
                  "optVal": "MIN,MAX,BOTH",
                  "postlabel": "",
                  "jscall": ""
                },
                {
                  "id": "dsp.15.3.4.13",
                  "target": "dynValue,12",
                  "prelabel": "",
                  "control": "select",
                  "type": "single",
                  "default": "Per Claim",
                  "optText": "Per Claim,Per Policy Period",
                  "altText": "Per Claim,Per Policy Period",
                  "optVal": "PC,PP",
                  "postlabel": "",
                  "jscall": ""
                }
              ]
            },
            {
              "id": "cnd.15.3.5",
              "field": "assistance.cover1",
              "value": "",
              "dynValue": "check_ip_chronic_limit('ICD001','~','~','~','~','~','~','~','~','~','~','~')",
              "clfactor": "10",
              "mandatory": "NO",
              "method": "get_request_country()",
              "source": "PACKAGE",
              "module": "P",
              "fieldData": "",
              "unit": "",
              "result": "",
              "configure": "NO",
              "display": [
                {
                  "id": "dsp.15.3.5.2",
                  "target": "dynValue,2",
                  "prelabel": "<span id='chr23'>IP Chronic Condition Limit",
                  "control": "select",
                  "type": "single",
                  "default": "LE",
                  "optText": "<=",
                  "altText": "LE",
                  "optVal": "LE",
                  "postlabel": "",
                  "jscall": "",
                  "lookup": ""
                },
                {
                  "id": "dsp.10.1.1.4",
                  "target": "dynValue,3",
                  "prelabel": "",
                  "control": "select",
                  "type": "single",
                  "default": "",
                  "optText": "fixed amount,% of Sum Insured",
                  "altText": "fixed amount,% of Sum Insured",
                  "optVal": "FA,SI",
                  "postlabel": "",
                  "jscall": ""
                },
                {
                  "id": "dsp.15.3.5.3",
                  "target": "dynValue,4",
                  "prelabel": "",
                  "control": "input",
                  "type": "text",
                  "default": "",
                  "postlabel": "",
                  "jscall": "onkeyup=isNumeric(this)",
                  "lookup": ""
                },
                {
                  "id": "dsp.15.3.5.4",
                  "target": "dynValue,5",
                  "prelabel": "",
                  "control": "input",
                  "type": "text",
                  "default": "OMR",
                  "optText": "",
                  "altText": "",
                  "optVal": "",
                  "disabled": "true",
                  "postlabel": "",
                  "jscall": ""
                },
                {
                  "id": "dsp.15.3.5.6",
                  "target": "dynValue,6",
                  "prelabel": "and Co-pay",
                  "control": "select",
                  "type": "single",
                  "default": "EQ",
                  "optText": "=",
                  "altText": "EQ",
                  "optVal": "EQ",
                  "postlabel": "",
                  "jscall": "",
                  "lookup": ""
                },
                {
                  "id": "dsp.15.3.5.7",
                  "target": "dynValue,7",
                  "prelabel": "",
                  "control": "input",
                  "type": "text",
                  "default": "",
                  "postlabel": "%",
                  "jscall": "onkeyup=isNumeric(this)",
                  "lookup": ""
                },
                {
                  "id": "dsp.15.3.5.8",
                  "target": "dynValue,8",
                  "prelabel": "with Deductable amount",
                  "control": "select",
                  "type": "single",
                  "default": "EQ",
                  "optText": "=",
                  "altText": "EQ",
                  "optVal": "EQ",
                  "postlabel": "",
                  "jscall": "",
                  "lookup": ""
                },
                {
                  "id": "dsp.15.3.5.9",
                  "target": "dynValue,9",
                  "prelabel": "",
                  "control": "input",
                  "type": "text",
                  "default": "",
                  "postlabel": "",
                  "jscall": "onkeyup=isNumeric(this)",
                  "lookup": ""
                },
                {
                  "id": "dsp.15.3.5.10",
                  "target": "dynValue,10",
                  "prelabel": "",
                  "control": "input",
                  "type": "text",
                  "default": "OMR",
                  "optText": "",
                  "altText": "",
                  "optVal": "OMR",
                  "disabled": "true",
                  "postlabel": "",
                  "jscall": ""
                },
                {
                  "id": "dsp.15.3.5.11",
                  "target": "",
                  "prelabel": "",
                  "control": "image",
                  "type": "image",
                  "imagepath": "EditIcon.gif",
                  "alt": "Select Currency",
                  "default": "",
                  "postlabel": "",
                  "jscall": "onclick=openRadioList('dsp.15.3.5.11','CURRENCY_GROUP','option')"
                },
                {
                  "id": "dsp.15.3.5.12",
                  "target": "dynValue,11",
                  "prelabel": "",
                  "control": "select",
                  "type": "single",
                  "default": "MIN",
                  "optText": "MIN,MAX,BOTH",
                  "altText": "MIN,MAX,BOTH",
                  "optVal": "MIN,MAX,BOTH",
                  "postlabel": "",
                  "jscall": ""
                },
                {
                  "id": "dsp.15.3.5.13",
                  "target": "dynValue,12",
                  "prelabel": "",
                  "control": "select",
                  "type": "single",
                  "default": "",
                  "optText": "Per Claim,Per Policy Period",
                  "altText": "Per Claim,Per Policy Period",
                  "optVal": "PC,PP",
                  "postlabel": "",
                  "jscall": ""
                }
              ]
            }
          ],
          "action": {
            "id": "act.15.3.1",
            "name": "Chronic"
          }
        }
      ]
    }
  ]
}
